[
    {
        "weapon_type": "WeaponAll",
        "weapon_type_name": "Weapon: All"
    },
    {
        "weapon_type": "WeaponAssaultRifle",
        "weapon_type_name": "Assault Rifle"
    },
    {
        "weapon_type": "WeaponBeamRifle",
        "weapon_type_name": "Beam Rifle"
    },
    {
        "weapon_type": "WeaponBow",
        "weapon_type_name": "Bow"
    },
    {
        "weapon_type": "WeaponHandCannon",
        "weapon_type_name": "Hand Cannon"
    },
    {
        "weapon_type": "WeaponHandGun",
        "weapon_type_name": "Handgun"
    },
    {
        "weapon_type": "WeaponLauncher",
        "weapon_type_name": "Launcher"
    },
    {
        "weapon_type": "WeaponMachineGun",
        "weapon_type_name": "Machine Gun"
    },
    {
        "weapon_type": "WeaponScoutRifle",
        "weapon_type_name": "Scout Rifle"
    },
    {
        "weapon_type": "WeaponShotGun",
        "weapon_type_name": "Shotgun"
    },
    {
        "weapon_type": "WeaponSniperRifle",
        "weapon_type_name": "Sniper Rifle"
    },
    {
        "weapon_type": "WeaponSubMachineGun",
        "weapon_type_name": "Submachine Gun"
    },
    {
        "weapon_type": "WeaponTacticalRifle",
        "weapon_type_name": "Tactical Rifle"
    }
]